sbc_utils/__init__.py
sbc_utils-1.0.2.dist-info/LICENSE
sbc_utils-1.0.2.dist-info/METADATA
sbc_utils-1.0.2.dist-info/WHEEL
sbc_utils-1.0.2.dist-info/top_level.txt
sbc_utils-1.0.2.dist-info/zip-safe
sbc_utils-1.0.2.dist-info/RECORD
