Metadata-Version: 2.1
Name: sbc-utils
Version: 1.0.2
Summary: Utility functions
Home-page: https://gitlab.stickboycreative.com/sbc-python/sbc_utils
Author: Abhinav Kotak
Author-email: in.abhi9@gmail.com
Maintainer: Abhinav Kotak
Maintainer-email: in.abhi9@gmail.com
License: MIT License
